Workbook

Sheet 1 Assumptions
A1: Assumptions — every input lives here
A2: Amber = change me. Red = unvalidated and material. Nothing downstream hard-codes a number.
A4: Input | B4: Value | C4: Unit | D4: Source / confidence
A5: — OBSERVED AT RAGAS COFFEE (design partner) —
A6: Counter staff cost | B6: 15000 | C6: ₹/month | D6: Founder, observed
A7: WeP annual subscription / AMC | B7: 7000 | C7: ₹/year | D7: Founder, observed — the real reference price
A8: WeP capex already sunk | B8: 12000 | C8: ₹ | D8: Band ₹9,990–25,500; midpoint [VALIDATE exact model]
A9: Bills observed | B9: 50 | C9: bills/week | D9: Founder, 1 week of use
A10: Working days | B10: 26 | C10: days/month | D10: Convention
A11: Counter hours | B11: 10 | C11: hours/day | D11: Convention [VALIDATE]
A13: — VOLUME SCENARIOS (drives cost more than the rate does) —
A14: Light shop — bills/month | B14: 215 | C14: bills | D14: =Ragas observed, 50/wk × 4.3
A15: Typical shop — bills/month | B15: 1500 | C15: bills | D15: [ASSUMPTION - VALIDATE] ~58/day
A16: Busy kirana — bills/month | B16: 6000 | C16: bills | D16: [ASSUMPTION - VALIDATE] ~230/day
A17: Utterances per bill | B17: 4 | C17: utterances | D17: [ASSUMPTION - VALIDATE] items + corrections + commands
A19: — COST DRIVERS —
A20: Cloud ASR rate | B20: 0.12 | C20: ₹/utterance | D20: [ASSUMPTION - VALIDATE] Sarvam rate unknown. THE most sensitive input.
A21: On-device ASR rate (post-port) | B21: 0 | C21: ₹/utterance | D21: Target state — the point of the Android build
A22: Cloud/platform cost per shop | B22: 12 | C22: ₹/month | D22: [ASSUMPTION - VALIDATE] Vercel + Supabase at scale
A23: Support cost per shop | B23: 25 | C23: ₹/month | D23: [ASSUMPTION - VALIDATE] must stay near-zero-touch
A24: Payment gateway share | B24: 0 | C24: ₹ | D24: We never touch funds — deliberate
A26: — PRICING (solve for, not fixed) —
A27: Tier 1 Single — price | B27: 399 | C27: ₹/month | D27: Anchored BELOW the ₹583/mo Ragas already pays WeP
A28: Tier 2 Growing — price | B28: 1999 | C28: ₹/month | D28: Undercuts Petpooja's ₹3,000–12,000 band
A29: Tier 3 Chain — price | B29: 7500 | C29: ₹/month | D29: [ASSUMPTION - VALIDATE] no Tier 3 product exists yet
A30: Shop kit (printer etc.) — sold at cost | B30: 4000 | C30: ₹ one-off | D30: Adoption lever, zero margin by design
A32: — GO TO MARKET —
A33: CAC — founder / referral | B33: 400 | C33: ₹ | D33: [ASSUMPTION - VALIDATE] time cost only
A34: CAC — printer dealer / reseller | B34: 1200 | C34: ₹ | D34: [ASSUMPTION - VALIDATE] one-off commission
A35: CAC — FMCG distributor channel | B35: 900 | C35: ₹ | D35: [ASSUMPTION - VALIDATE] unproven channel
A36: Monthly churn — Tier 1 | B36: 0.04 | C36: fraction | D36: [ASSUMPTION - VALIDATE] 4%/mo = ~25mo life. SME SaaS is worse than this.
A37: Monthly churn — Tier 2 | B37: 0.02 | C37: fraction | D37: [ASSUMPTION - VALIDATE]
A38: Monthly churn — Tier 3 | B38: 0.01 | C38: fraction | D38: [ASSUMPTION - VALIDATE]
A39: Time saved per bill vs typing | B39: 20 | C39: seconds | D39: [ASSUMPTION - VALIDATE] NOT measured. Instrument this next.

Sheet 2 Retailer ROI
A1: What the shop gets back — by volume, not by tier
A2: The finding that matters: at low volume the value is NOT time saved. It is the AMC, the capex and knowing your own numbers.
A4: Line | B4: Light (Ragas) | C4: Typical | D4: Busy kirana | E4: Note
A5: Bills per month | B5: ='1 Assumptions'!$B$14 | C5: ='1 Assumptions'!$B$15 | D5: ='1 Assumptions'!$B$16
A6: Staff cost per second | B6: ='1 Assumptions'!$B$6/('1 Assumptions'!$B$10*'1 Assumptions'!$B$11*3600) | C6: ='1 Assumptions'!$B$6/('1 Assumptions'!$B$10*'1 Assumptions'!$B$11*3600) | D6: ='1 Assumptions'!$B$6/('1 Assumptions'!$B$10*'1 Assumptions'!$B$11*3600) | E6: ₹15,000 ÷ working seconds
A7: Time saved (seconds/month) | B7: ='1 Assumptions'!$B$14*'1 Assumptions'!$B$42 | C7: ='1 Assumptions'!$B$15*'1 Assumptions'!$B$42 | D7: ='1 Assumptions'!$B$16*'1 Assumptions'!$B$42 | E7: bills × seconds saved [VALIDATE]
A8: Labour value released | B8: ='1 Assumptions'!$B$14*'1 Assumptions'!$B$42*'1 Assumptions'!$B$6/('1 Assumptions'!$B$10*'1 Assumptions'!$B$11*3600) | C8: ='1 Assumptions'!$B$15*'1 Assumptions'!$B$42*'1 Assumptions'!$B$6/('1 Assumptions'!$B$10*'1 Assumptions'!$B$11*3600) | D8: ='1 Assumptions'!$B$16*'1 Assumptions'!$B$42*'1 Assumptions'!$B$6/('1 Assumptions'!$B$10*'1 Assumptions'!$B$11*3600) | E8: Only meaningful at volume — see note below
A9: AMC avoided | B9: ='1 Assumptions'!$B$7/12 | C9: ='1 Assumptions'!$B$7/12 | D9: ='1 Assumptions'!$B$7/12 | E9: ₹7,000/yr Ragas pays WeP today
A10: Capex avoided (5-yr amortised) | B10: ='1 Assumptions'!$B$8/60 | C10: ='1 Assumptions'!$B$8/60 | D10: ='1 Assumptions'!$B$8/60 | E10: Applies to the NEXT machine, not the sunk one
A11: Gross monthly benefit | B11: ='1 Assumptions'!$B$14*'1 Assumptions'!$B$42*'1 Assumptions'!$B$6/('1 Assumptions'!$B$10*'1 Assumptions'!$B$11*3600)+'1 Assumptions'!$B$7/12+'1 Assumptions'!$B$8/60 | C11: ='1 Assumptions'!$B$15*'1 Assumptions'!$B$42*'1 Assumptions'!$B$6/('1 Assumptions'!$B$10*'1 Assumptions'!$B$11*3600)+'1 Assumptions'!$B$7/12+'1 Assumptions'!$B$8/60 | D11: ='1 Assumptions'!$B$16*'1 Assumptions'!$B$42*'1 Assumptions'!$B$6/('1 Assumptions'!$B$10*'1 Assumptions'!$B$11*3600)+'1 Assumptions'!$B$7/12+'1 Assumptions'!$B$8/60
A12: Less: our Tier 1 subscription | B12: =-'1 Assumptions'!$B$29 | C12: =-'1 Assumptions'!$B$29 | D12: =-'1 Assumptions'!$B$29
A13: NET monthly benefit | B13: ='1 Assumptions'!$B$14*'1 Assumptions'!$B$42*'1 Assumptions'!$B$6/('1 Assumptions'!$B$10*'1 Assumptions'!$B$11*3600)+'1 Assumptions'!$B$7/12+'1 Assumptions'!$B$8/60-'1 Assumptions'!$B$29 | C13: ='1 Assumptions'!$B$15*'1 Assumptions'!$B$42*'1 Assumptions'!$B$6/('1 Assumptions'!$B$10*'1 Assumptions'!$B$11*3600)+'1 Assumptions'!$B$7/12+'1 Assumptions'!$B$8/60-'1 Assumptions'!$B$29 | D13: ='1 Assumptions'!$B$16*'1 Assumptions'!$B$42*'1 Assumptions'!$B$6/('1 Assumptions'!$B$10*'1 Assumptions'!$B$11*3600)+'1 Assumptions'!$B$7/12+'1 Assumptions'!$B$8/60-'1 Assumptions'!$B$29
A14: Payback on the ₹4,000 kit (months) | B14: =IF(('1 Assumptions'!$B$14*'1 Assumptions'!$B$42*'1 Assumptions'!$B$6/('1 Assumptions'!$B$10*'1 Assumptions'!$B$11*3600)+'1 Assumptions'!$B$7/12+'1 Assumptions'!$B$8/60-'1 Assumptions'!$B$29)>0,'1 Assumptions'!$B$32/('1 Assumptions'!$B$14*'1 Assumptions'!$B$42*'1 Assumptions'!$B$6/('1 Assumptions'!$B$10*'1 Assumptions'!$B$11*3600)+'1 Assumptions'!$B$7/12+'1 Assumptions'!$B$8/60-'1 Assumptions'!$B$29),"never") | C14: =IF(('1 Assumptions'!$B$15*'1 Assumptions'!$B$42*'1 Assumptions'!$B$6/('1 Assumptions'!$B$10*'1 Assumptions'!$B$11*3600)+'1 Assumptions'!$B$7/12+'1 Assumptions'!$B$8/60-'1 Assumptions'!$B$29)>0,'1 Assumptions'!$B$32/('1 Assumptions'!$B$15*'1 Assumptions'!$B$42*'1 Assumptions'!$B$6/('1 Assumptions'!$B$10*'1 Assumptions'!$B$11*3600)+'1 Assumptions'!$B$7/12+'1 Assumptions'!$B$8/60-'1 Assumptions'!$B$29),"never") | D14: =IF(('1 Assumptions'!$B$16*'1 Assumptions'!$B$42*'1 Assumptions'!$B$6/('1 Assumptions'!$B$10*'1 Assumptions'!$B$11*3600)+'1 Assumptions'!$B$7/12+'1 Assumptions'!$B$8/60-'1 Assumptions'!$B$29)>0,'1 Assumptions'!$B$32/('1 Assumptions'!$B$16*'1 Assumptions'!$B$42*'1 Assumptions'!$B$6/('1 Assumptions'!$B$10*'1 Assumptions'!$B$11*3600)+'1 Assumptions'!$B$7/12+'1 Assumptions'!$B$8/60-'1 Assumptions'!$B$29),"never") | E14: Only hardware is at risk — no lock-in
A16: THE HONEST READ
A17: At Ragas volumes the labour saving is small — a low-volume café does not buy this to save time. It buys it to stop paying the AMC, to avoid the next machine, and because the owner does not currently know his own margins. That is a DIFFERENT sales pitch from the one the deck would naturally make, and it is the true one for Tier 1. Labour savings only dominate at kirana volume.

Sheet 3 Unit economics
A1: Our side — per shop, per month
A2: Cloud ASR vs on-device shown side by side. The gap between them is the business case for the Android build.
A4: Metric | B4: T1 cloud ASR | C4: T1 on-device | D4: T2 Growing | E4: T3 Chain | F4: Note
A5: Utterances / month | B5: ='1 Assumptions'!$B$15*'1 Assumptions'!$B$17 | C5: ='1 Assumptions'!$B$15*'1 Assumptions'!$B$17 | D5: ='1 Assumptions'!$B$15*'1 Assumptions'!$B$17*3 | E5: ='1 Assumptions'!$B$16*'1 Assumptions'!$B$17*8 | F5: Volume, not outlet count, drives cost
A6: ARPU | B6: ='1 Assumptions'!$B$29 | C6: ='1 Assumptions'!$B$29 | D6: ='1 Assumptions'!$B$30 | E6: ='1 Assumptions'!$B$31 | F6: Tier 1 sits below the ₹583 Ragas already pays
A7: ASR cost | B7: =-'1 Assumptions'!$B$15*'1 Assumptions'!$B$17*'1 Assumptions'!$B$21 | C7: =-'1 Assumptions'!$B$15*'1 Assumptions'!$B$17*'1 Assumptions'!$B$22 | D7: =-'1 Assumptions'!$B$15*'1 Assumptions'!$B$17*3*'1 Assumptions'!$B$22 | E7: =-'1 Assumptions'!$B$16*'1 Assumptions'!$B$17*8*'1 Assumptions'!$B$22 | F7: T2/T3 assume the port has shipped
A8: Platform | B8: =-'1 Assumptions'!$B$23 | C8: =-'1 Assumptions'!$B$23 | D8: =-'1 Assumptions'!$B$23*3 | E8: =-'1 Assumptions'!$B$23*8
A9: Support | B9: =-'1 Assumptions'!$B$24 | C9: =-'1 Assumptions'!$B$24 | D9: =-'1 Assumptions'!$B$24*2 | E9: =-'1 Assumptions'!$B$24*4 | F9: Higher tiers get humans
A10: Gross profit | B10: ='1 Assumptions'!$B$29-'1 Assumptions'!$B$15*'1 Assumptions'!$B$17*'1 Assumptions'!$B$21-'1 Assumptions'!$B$23-'1 Assumptions'!$B$24 | C10: ='1 Assumptions'!$B$29-'1 Assumptions'!$B$15*'1 Assumptions'!$B$17*'1 Assumptions'!$B$22-'1 Assumptions'!$B$23-'1 Assumptions'!$B$24 | D10: ='1 Assumptions'!$B$30-'1 Assumptions'!$B$15*'1 Assumptions'!$B$17*3*'1 Assumptions'!$B$22-'1 Assumptions'!$B$23*3-'1 Assumptions'!$B$24*2 | E10: ='1 Assumptions'!$B$31-'1 Assumptions'!$B$16*'1 Assumptions'!$B$17*8*'1 Assumptions'!$B$22-'1 Assumptions'!$B$23*8-'1 Assumptions'!$B$24*4
A11: Gross margin % | B11: =B10/B6 | C11: =C10/C6 | D11: =D10/D6 | E11: =E10/E6
A12: CAC (blended) | B12: =('1 Assumptions'!$B$36+'1 Assumptions'!$B$37)/2 | C12: =('1 Assumptions'!$B$36+'1 Assumptions'!$B$37)/2 | D12: ='1 Assumptions'!$B$37 | E12: ='1 Assumptions'!$B$37*3 | F12: Tier 1 must be reseller-led; founder-led does not scale
A13: CAC payback (months) | B13: =IF(B10>0,B12/B10,"never") | C13: =IF(C10>0,C12/C10,"never") | D13: =IF(D10>0,D12/D10,"never") | E13: =IF(E10>0,E12/E10,"never")
A14: Monthly churn | B14: ='1 Assumptions'!$B$39 | C14: ='1 Assumptions'!$B$39 | D14: ='1 Assumptions'!$B$40 | E14: ='1 Assumptions'!$B$41
A15: Expected life (months) | B15: =1/'1 Assumptions'!$B$39 | C15: =1/'1 Assumptions'!$B$39 | D15: =1/'1 Assumptions'!$B$40 | E15: =1/'1 Assumptions'!$B$41
A16: LTV (gross profit basis) | B16: =B10/'1 Assumptions'!$B$39 | C16: =C10/'1 Assumptions'!$B$39 | D16: =D10/'1 Assumptions'!$B$40 | E16: =E10/'1 Assumptions'!$B$41
A17: LTV : CAC | B17: =IF(B12>0,B16/B12,0) | C17: =IF(C12>0,C16/C12,0) | D17: =IF(D12>0,D16/D12,0) | E17: =IF(E12>0,E16/E12,0)
A18: BREAK-EVEN cloud ASR rate (₹/utterance) | B18: =(B6+B8+B9)/B5 | C18: Above this rate, Tier 1 cannot be profitable on cloud ASR at any volume. This makes the sheet answer the question instead of depending on an unvalidated Sarvam quote.
A20: READ THIS BEFORE THE DECK
A21: Compare B and C. On cloud ASR at the assumed rate, a typical-volume Tier 1 shop is thin or negative — the ceiling in CLAUDE.md was right. On-device takes the same shop to near-100% gross margin. THAT is the funding argument: we are not raising to build features, we are raising to move the inference on-device and turn a negative unit into a positive one. If the Sarvam rate in Assumptions is wrong, this entire sheet moves — validate it first.

Sheet 4 Three-year build
A1: Company build — solo founder, capital-efficient
A2: Shop counts are targets, not forecasts. Opex is the funding ask, backed out rather than guessed.
A4: Line | B4: Y1 | C4: Y2 | D4: Y3 | E4: Note
A5: Tier 1 shops (end of year) | B5: 60 | C5: 600 | D5: 2500 | E5: [ASSUMPTION - VALIDATE] 60 in Y1 is founder-led reach
A6: Tier 2 shops | B6: 0 | C6: 25 | D6: 150 | E6: Only after order mgmt + multi-counter exist
A7: Tier 3 shops | B7: 0 | C7: 0 | D7: 10 | E7: No Tier 3 product before Y3
A8: Revenue | B8: =B5*'1 Assumptions'!$B$29*6 | C8: =(B5+C5)/2*'1 Assumptions'!$B$29*12+C6*'1 Assumptions'!$B$30*6 | D8: =(C5+D5)/2*'1 Assumptions'!$B$29*12+(C6+D6)/2*'1 Assumptions'!$B$30*12+D7*'1 Assumptions'!$B$31*6 | E8: Half-year weighting on new cohorts
A9: Gross profit | B9: =B8*0.55 | C9: =C8*0.85 | D9: =D8*0.9 | E9: Margin rises as the port lands — Y1 still cloud ASR
A10: Engineering (ASR/Android hire) | B10: 1800000 | C10: 3600000 | D10: 5400000 | E10: 1 → 2 → 3 engineers [VALIDATE Chennai comp]
A11: Field / onboarding | B11: 0 | C11: 900000 | D11: 2400000 | E11: Founder does Y1
A12: Founder | B12: 0 | C12: 600000 | D12: 1200000 | E12: Unpaid Y1 — this is the capital efficiency story
A13: Infra, tools, travel | B13: 250000 | C13: 600000 | D13: 1200000
A14: Total opex | B14: =SUM(B10:B13) | C14: =SUM(C10:C13) | D14: =SUM(D10:D13)
A15: EBITDA | B15: =B9-B14 | C15: =C9-C14 | D15: =D9-D14
A16: Cumulative cash need | B16: =-B15 | C16: =-B15-C15 | D16: =-B15-C15-D15 | E16: → the funding ask, backed out of the plan
A18: FUNDING ASK
A19: ="Ask ≈ ₹"&TEXT(ROUNDUP((-B15-C15)/100000,0)*100000,"#,##0")&" (covers Y1+Y2 with headroom; Y3 assumes revenue or a second round)"

Sheet 5 Sensitivity
A1: The three that swing it — expect these questions first
A2: Change the amber cell in Assumptions and watch sheet 3 move.
A4: Variable | B4: Assumed | C4: If 2× worse | D4: Effect | E4: Why it is the first question
A5: Cloud ASR ₹/utterance | B5: ='1 Assumptions'!$B$21 | C5: ='1 Assumptions'!$B$21*2 | D5: Tier 1 gross profit inverts | E5: Unvalidated, and the single largest cost line before the port. Get the real Sarvam rate.
A6: Utterances per bill | B6: ='1 Assumptions'!$B$17 | C6: ='1 Assumptions'!$B$17*2 | D6: ASR cost doubles | E6: Corrections and retries count. Measurable from the utterance log we already keep.
A7: Monthly churn T1 | B7: ='1 Assumptions'!$B$39 | C7: ='1 Assumptions'!$B$39*2 | D7: LTV halves | E7: One week at one shop tells us nothing about retention. This is the weakest number in the model.
A8: Time saved per bill | B8: ='1 Assumptions'!$B$42 | C8: ='1 Assumptions'!$B$42/2 | D8: Retailer payback lengthens | E8: Never measured. Instrument billing-duration before claiming it in a sales conversation.
A9: Tier 1 price | B9: ='1 Assumptions'!$B$29 | C9: =599 | D9: Margin and adoption both move | E9: ₹583/mo is what Ragas already pays WeP. That is the ceiling that matters, not Vyapar's free tier.
